siin_studio/__init__.py
siin_studio/calls.py
siin_studio/cli.py
siin_studio/client.py
siin_studio_cli-0.2.4.dist-info/METADATA
siin_studio_cli-0.2.4.dist-info/WHEEL
siin_studio_cli-0.2.4.dist-info/entry_points.txt
siin_studio_cli-0.2.4.dist-info/top_level.txt
siin_studio_cli-0.2.4.dist-info/RECORD
