Metadata-Version: 2.4
Name: siin-studio-cli
Version: 0.2.4
Summary: Add your description here
Requires-Python: >=3.11
Requires-Dist: click>=8.2.1
Requires-Dist: requests>=2.32.5
Requires-Dist: tqdm>=4.67.1
